setup.py
src/digimat/__init__.py
src/digimat.lutron.egg-info/PKG-INFO
src/digimat.lutron.egg-info/SOURCES.txt
src/digimat.lutron.egg-info/dependency_links.txt
src/digimat.lutron.egg-info/namespace_packages.txt
src/digimat.lutron.egg-info/not-zip-safe
src/digimat.lutron.egg-info/requires.txt
src/digimat.lutron.egg-info/top_level.txt
src/digimat/lutron/__init__.py
src/digimat/lutron/collections.py
src/digimat/lutron/hvac.py
src/digimat/lutron/lutron.py
src/digimat/lutron/message.py
src/digimat/lutron/object.py
src/digimat/lutron/output.py