Metadata-Version: 1.1
Name: digimat.lutron
Version: 0.0.5
Summary: Lutron processor communication
Home-page: https://www.digimat.ch
Author: Frederic Hess
Author-email: fhess@st-sa.ch
License: PSF
Platform: UNKNOWN
Classifier: Development Status :: 4 - Beta
Classifier: Programming Language :: Python :: 3
